pygremlinbox_ms_lpl/__init__.py
pygremlinbox_ms_lpl-1.4.0.dist-info/METADATA
pygremlinbox_ms_lpl-1.4.0.dist-info/WHEEL
pygremlinbox_ms_lpl-1.4.0.dist-info/top_level.txt
pygremlinbox_ms_lpl-1.4.0.dist-info/RECORD
